luie/__init__.py
luie/labels/__init__.py
luie/labels/named_entity_recognition/__init__.py
luie/labels/named_entity_recognition/klue.py
luie/labels/named_entity_recognition/korean_corpus.py
luie/labels/relation_extraction/__init__.py
luie/labels/relation_extraction/ai_hub.py
luie/labels/relation_extraction/klue.py
luie/labels/semantic_role_labeling/__init__.py
luie/labels/semantic_role_labeling/korean_corpus.py
luie/luie.py
luie/models/__init__.py
luie/models/sequence_labeling.py
luie/models/text_classification.py
luie/modules/__init__.py
luie/modules/ner_module.py
luie/tokenizers/__init__.py
luie/tokenizers/kocharelectra.py
luie-0.2.1.dist-info/METADATA
luie-0.2.1.dist-info/WHEEL
luie-0.2.1.dist-info/RECORD
