Metadata-Version: 2.1
Name: luie
Version: 0.2.1
Summary: 
Author: Your Name
Author-email: you@example.com
Requires-Python: >=3.8,<4.0
Classifier: Programming Language :: Python :: 3
Classifier: Programming Language :: Python :: 3.8
Classifier: Programming Language :: Python :: 3.9
Classifier: Programming Language :: Python :: 3.10
Classifier: Programming Language :: Python :: 3.11
Requires-Dist: fire (>=0.5.0,<0.6.0)
Requires-Dist: kodali (>=0.3.0,<0.4.0)
Requires-Dist: seqeval (>=1.2.2,<2.0.0)
Requires-Dist: strenum (>=0.4.15,<0.5.0)
Requires-Dist: transformers (>=4.32.1,<5.0.0)
